PyCpuSimulator/Version.py
PyCpuSimulator/__init__.py
PyCpuSimulator/Avr/HexFile.py
PyCpuSimulator/Avr/__init__.py
PyCpuSimulator/Avr/opcodes.yml
PyCpuSimulator/BinaryFormat/HexFile.py
PyCpuSimulator/BinaryFormat/ObjDump.py
PyCpuSimulator/BinaryFormat/__init__.py
PyCpuSimulator/Config/ConfigInstall.py
PyCpuSimulator/Config/__init__.py
PyCpuSimulator/Config/logging.yml
PyCpuSimulator/Core/Core.py
PyCpuSimulator/Core/CoreAst.py
PyCpuSimulator/Core/CoreHdlParser.py
PyCpuSimulator/Core/Instruction.py
PyCpuSimulator/Core/__init__.py
PyCpuSimulator/Logging/Logging.py
PyCpuSimulator/Logging/__init__.py
PyCpuSimulator/Math/Functions.py
PyCpuSimulator/Math/Interval.py
PyCpuSimulator/Math/__init__.py
PyCpuSimulator/Tools/BinaryNumber.py
PyCpuSimulator/Tools/Path.py
PyCpuSimulator/Tools/RevisionVersion.py
PyCpuSimulator/Tools/__init__.py
PyCpuSimulator-0.2.1.dist-info/DESCRIPTION.rst
PyCpuSimulator-0.2.1.dist-info/METADATA
PyCpuSimulator-0.2.1.dist-info/RECORD
PyCpuSimulator-0.2.1.dist-info/WHEEL
PyCpuSimulator-0.2.1.dist-info/metadata.json
PyCpuSimulator-0.2.1.dist-info/top_level.txt
