Metadata-Version: 2.0
Name: PyCpuSimulator
Version: 0.2.1
Summary: PyCpuSimulator is a CPU simulator
Home-page: https://github.com/FabriceSalvaire/PyCpuSimulator
Author: Fabrice Salvaire
Author-email: fabrice.salvaire@orange.fr
License: GPLv3
Keywords: cpu core avr simulator micro-code
Platform: any
Classifier: Topic :: Scientific/Engineering
Classifier: Intended Audience :: Education
Classifier: Development Status :: 3 - Alpha
Classifier: License :: OSI Approved :: GNU General Public License v3 (GPLv3)
Classifier: Operating System :: OS Independent
Classifier: Programming Language :: Python :: 3.4
Requires-Dist: PyYAML
Requires-Dist: numpy
Requires-Dist: ansicolor
Requires-Dist: ply
